myigbot/__init__.py
myigbot-0.2.5.dist-info/LICENCE
myigbot-0.2.5.dist-info/METADATA
myigbot-0.2.5.dist-info/WHEEL
myigbot-0.2.5.dist-info/top_level.txt
myigbot-0.2.5.dist-info/RECORD
