Metadata-Version: 2.1
Name: myigbot
Version: 0.2.5
Summary: MyIGBot is a Private API for Instagram to like, follow, comment, view & intaract with stories, upload post & stories, get all information about a user/posts and get posts based on locations/hashtags. It also supports proxy.
Home-page: https://github.com/b31ngD3v/MyIGBot
Author: Pramurta Sinha (b31ngD3v)
Author-email: contact.pycoder@gmail.com
License: MIT
Keywords: instagram,bot,api,instagram-api,instagram-private-api,instagram-bot,private-api,myigbot,my-ig-bot
Platform: UNKNOWN
Classifier: License :: OSI Approved :: MIT License
Classifier: Programming Language :: Python :: 3.6
Classifier: Programming Language :: Python :: 3.7
Classifier: Programming Language :: Python :: 3.8
Classifier: Programming Language :: Python :: 3.9
Requires-Dist: requests
Requires-Dist: bs4
Requires-Dist: datetime
